DL_Track_US/DL_Track_US_GUI.py
DL_Track_US/DL_Track_US_GUI.spec
DL_Track_US/__init__.py
DL_Track_US/__main__.py
DL_Track_US/installer.iss
DL_Track_US/mkdocs.yml
DL_Track_US/docs/about_us.md
DL_Track_US/docs/api_advanced_analysis.md
DL_Track_US/docs/api_helpers.md
DL_Track_US/docs/api_index.md
DL_Track_US/docs/api_model_training.md
DL_Track_US/docs/automated_image_analysis.md
DL_Track_US/docs/automated_image_analysis_test.md
DL_Track_US/docs/automated_video_analysis.md
DL_Track_US/docs/automated_video_analysis_test.md
DL_Track_US/docs/code_of_conduct.md
DL_Track_US/docs/contributing.md
DL_Track_US/docs/crop_video.md
DL_Track_US/docs/index.md
DL_Track_US/docs/inspecting_masks.md
DL_Track_US/docs/installation.md
DL_Track_US/docs/manual_image_analysis.md
DL_Track_US/docs/manual_image_video_analysis_test.md
DL_Track_US/docs/manual_video_analysis.md
DL_Track_US/docs/model_training_test.md
DL_Track_US/docs/news.md
DL_Track_US/docs/remove_video_parts.md
DL_Track_US/docs/resize_video.md
DL_Track_US/docs/training_your_own_networks.md
DL_Track_US/docs/md_graphics/DLTrack_logo.png
DL_Track_US/docs/md_graphics/DLTrack_mainUI.png
DL_Track_US/docs/md_graphics/aia/analysis_parameters.PNG
DL_Track_US/docs/md_graphics/aia/analysis_type_image.PNG
DL_Track_US/docs/md_graphics/aia/apo_model_path.PNG
DL_Track_US/docs/md_graphics/aia/apo_model_path_2.PNG
DL_Track_US/docs/md_graphics/aia/calibrate.png
DL_Track_US/docs/md_graphics/aia/calibrate_button.png
DL_Track_US/docs/md_graphics/aia/calibration_result.png
DL_Track_US/docs/md_graphics/aia/error.PNG
DL_Track_US/docs/md_graphics/aia/fasc_model_path.PNG
DL_Track_US/docs/md_graphics/aia/fasc_model_path_2.PNG
DL_Track_US/docs/md_graphics/aia/fascial_orientation.PNG
DL_Track_US/docs/md_graphics/aia/filter_fascicles.PNG
DL_Track_US/docs/md_graphics/aia/filter_fascicles_2.PNG
DL_Track_US/docs/md_graphics/aia/flip_flag.PNG
DL_Track_US/docs/md_graphics/aia/flip_flag_2.PNG
DL_Track_US/docs/md_graphics/aia/flip_flag_button.PNG
dl_track_us-0.3.0.dist-info/METADATA
dl_track_us-0.3.0.dist-info/WHEEL
dl_track_us-0.3.0.dist-info/licenses/LICENSE
dl_track_us-0.3.0.dist-info/RECORD
