Metadata-Version: 2.4
Name: DL_Track_US
Version: 0.3.0
Summary: Automatic analysis of logitudinal muscle ultrasonography images
Project-URL: Homepage, https://github.com/PaulRitsche/DL_Track_US
Project-URL: Bug Tracker, https://github.com/PaulRitsche/DL_Track_US/issues
Project-URL: Documentation, https://paulritsche.github.io/DL_Track_US/
Author-email: Paul Ritsche <paul.ritsche@unibas.ch>, Olivier Seynnes <oliviers@nih.no>, Neil Cronin <neil.j.cronin@jyu.fi>
License-File: LICENSE
Classifier: Intended Audience :: Science/Research
Classifier: License :: OSI Approved :: Apache Software License
Classifier: Operating System :: OS Independent
Classifier: Programming Language :: Python :: 3
Requires-Python: >=3.10
Requires-Dist: ctktooltip==0.8
Requires-Dist: customtkinter==5.2.2
Requires-Dist: keras==2.10.0
Requires-Dist: matplotlib==3.6.1
Requires-Dist: numpy==1.23.4
Requires-Dist: opencv-contrib-python==4.6.0.66
Requires-Dist: openpyxl==3.0.10
Requires-Dist: pandas==1.5.1
Requires-Dist: pandastable==0.13.1
Requires-Dist: pillow==9.2.0
Requires-Dist: pre-commit==2.17.0
Requires-Dist: scikit-image==0.19.3
Requires-Dist: scikit-learn==1.1.2
Requires-Dist: sewar==0.4.5
Requires-Dist: shapely==2.0.5
Requires-Dist: tensorflow==2.10.0
Requires-Dist: tqdm==4.64.1
